[
    {
        "status": "completed", 
        "check_run_url": "https://api.github.com/repos/CHChang810716/hunter/check-runs/1524527588", 
        "name": "Arkitekto analyze-cxx17 ubuntu-16.04", 
        "run_id": 410814899, 
        "url": "https://api.github.com/repos/CHChang810716/hunter/actions/jobs/1524527588", 
        "html_url": "https://github.com/CHChang810716/hunter/runs/1524527588", 
        "completed_at": "2020-12-09T14:34:24Z", 
        "run_url": "https://api.github.com/repos/CHChang810716/hunter/actions/runs/410814899", 
        "node_id": "MDg6Q2hlY2tSdW4xNTI0NTI3NTg4", 
        "steps": [
            {
                "status": "completed", 
                "name": "Set up job", 
                "number": 1, 
                "completed_at": "2020-12-09T14:33:55.000Z", 
                "started_at": "2020-12-09T14:33:53.000Z", 
                "conclusion": "success"
            }, 
            {
                "status": "completed", 
                "name": "Git checkout with submodules", 
                "number": 2, 
                "completed_at": "2020-12-09T14:34:10.000Z", 
                "started_at": "2020-12-09T14:33:55.000Z", 
                "conclusion": "success"
            }, 
            {
                "status": "completed", 
                "name": "Set up Python", 
                "number": 3, 
                "completed_at": "2020-12-09T14:34:10.000Z", 
                "started_at": "2020-12-09T14:34:10.000Z", 
                "conclusion": "success"
            }, 
            {
                "status": "completed", 
                "name": "Set up Python environment variable (Unix)", 
                "number": 4, 
                "completed_at": "2020-12-09T14:34:10.000Z", 
                "started_at": "2020-12-09T14:34:10.000Z", 
                "conclusion": "success"
            }, 
            {
                "status": "completed", 
                "name": "Set up Python environment variable (Windows)", 
                "number": 5, 
                "completed_at": "2020-12-09T14:34:10.000Z", 
                "started_at": "2020-12-09T14:34:10.000Z", 
                "conclusion": "skipped"
            }, 
            {
                "status": "completed", 
                "name": "Extract branch name", 
                "number": 6, 
                "completed_at": "2020-12-09T14:34:10.000Z", 
                "started_at": "2020-12-09T14:34:10.000Z", 
                "conclusion": "success"
            }, 
            {
                "status": "completed", 
                "name": "Upgrade pip", 
                "number": 7, 
                "completed_at": "2020-12-09T14:34:15.000Z", 
                "started_at": "2020-12-09T14:34:10.000Z", 
                "conclusion": "success"
            }, 
            {
                "status": "completed", 
                "name": "Build on Unix", 
                "number": 8, 
                "completed_at": "2020-12-09T14:34:23.000Z", 
                "started_at": "2020-12-09T14:34:15.000Z", 
                "conclusion": "failure"
            }, 
            {
                "status": "completed", 
                "name": "Build on Windows", 
                "number": 9, 
                "completed_at": "2020-12-09T14:34:23.000Z", 
                "started_at": "2020-12-09T14:34:23.000Z", 
                "conclusion": "skipped"
            }, 
            {
                "status": "completed", 
                "name": "Post Git checkout with submodules", 
                "number": 18, 
                "completed_at": "2020-12-09T14:34:24.000Z", 
                "started_at": "2020-12-09T14:34:23.000Z", 
                "conclusion": "success"
            }, 
            {
                "status": "completed", 
                "name": "Complete job", 
                "number": 19, 
                "completed_at": "2020-12-09T14:34:24.000Z", 
                "started_at": "2020-12-09T14:34:24.000Z", 
                "conclusion": "success"
            }
        ], 
        "head_sha": "950960e8f1d67f7bc64155417f4a8e8ccebbad64", 
        "started_at": "2020-12-09T14:33:53Z", 
        "id": 1524527588, 
        "conclusion": "failure"
    }, 
    {
        "status": "completed", 
        "check_run_url": "https://api.github.com/repos/CHChang810716/hunter/check-runs/1524527571", 
        "name": "Arkitekto android-ndk-r17-api-24-arm64-v8a-clang-libcxx14 ubuntu-16.04", 
        "run_id": 410814899, 
        "url": "https://api.github.com/repos/CHChang810716/hunter/actions/jobs/1524527571", 
        "html_url": "https://github.com/CHChang810716/hunter/runs/1524527571", 
        "completed_at": "2020-12-09T14:35:01Z", 
        "run_url": "https://api.github.com/repos/CHChang810716/hunter/actions/runs/410814899", 
        "node_id": "MDg6Q2hlY2tSdW4xNTI0NTI3NTcx", 
        "steps": [
            {
                "status": "completed", 
                "name": "Set up job", 
                "number": 1, 
                "completed_at": "2020-12-09T14:33:58.000Z", 
                "started_at": "2020-12-09T14:33:52.000Z", 
                "conclusion": "success"
            }, 
            {
                "status": "completed", 
                "name": "Git checkout with submodules", 
                "number": 2, 
                "completed_at": "2020-12-09T14:34:02.000Z", 
                "started_at": "2020-12-09T14:33:58.000Z", 
                "conclusion": "success"
            }, 
            {
                "status": "completed", 
                "name": "Set up Python", 
                "number": 3, 
                "completed_at": "2020-12-09T14:34:02.000Z", 
                "started_at": "2020-12-09T14:34:02.000Z", 
                "conclusion": "success"
            }, 
            {
                "status": "completed", 
                "name": "Set up Python environment variable (Unix)", 
                "number": 4, 
                "completed_at": "2020-12-09T14:34:02.000Z", 
                "started_at": "2020-12-09T14:34:02.000Z", 
                "conclusion": "success"
            }, 
            {
                "status": "completed", 
                "name": "Set up Python environment variable (Windows)", 
                "number": 5, 
                "completed_at": "2020-12-09T14:34:02.000Z", 
                "started_at": "2020-12-09T14:34:02.000Z", 
                "conclusion": "skipped"
            }, 
            {
                "status": "completed", 
                "name": "Extract branch name", 
                "number": 6, 
                "completed_at": "2020-12-09T14:34:02.000Z", 
                "started_at": "2020-12-09T14:34:02.000Z", 
                "conclusion": "success"
            }, 
            {
                "status": "completed", 
                "name": "Upgrade pip", 
                "number": 7, 
                "completed_at": "2020-12-09T14:34:04.000Z", 
                "started_at": "2020-12-09T14:34:02.000Z", 
                "conclusion": "success"
            }, 
            {
                "status": "completed", 
                "name": "Build on Unix", 
                "number": 8, 
                "completed_at": "2020-12-09T14:35:01.000Z", 
                "started_at": "2020-12-09T14:34:04.000Z", 
                "conclusion": "failure"
            }, 
            {
                "status": "completed", 
                "name": "Build on Windows", 
                "number": 9, 
                "completed_at": "2020-12-09T14:35:01.000Z", 
                "started_at": "2020-12-09T14:35:01.000Z", 
                "conclusion": "skipped"
            }, 
            {
                "status": "completed", 
                "name": "Post Git checkout with submodules", 
                "number": 18, 
                "completed_at": "2020-12-09T14:35:01.000Z", 
                "started_at": "2020-12-09T14:35:01.000Z", 
                "conclusion": "success"
            }, 
            {
                "status": "completed", 
                "name": "Complete job", 
                "number": 19, 
                "completed_at": "2020-12-09T14:35:01.000Z", 
                "started_at": "2020-12-09T14:35:01.000Z", 
                "conclusion": "success"
            }
        ], 
        "head_sha": "950960e8f1d67f7bc64155417f4a8e8ccebbad64", 
        "started_at": "2020-12-09T14:33:52Z", 
        "id": 1524527571, 
        "conclusion": "failure"
    }, 
    {
        "status": "completed", 
        "check_run_url": "https://api.github.com/repos/CHChang810716/hunter/check-runs/1524527472", 
        "name": "Arkitekto clang-cxx17 ubuntu-16.04", 
        "run_id": 410814899, 
        "url": "https://api.github.com/repos/CHChang810716/hunter/actions/jobs/1524527472", 
        "html_url": "https://github.com/CHChang810716/hunter/runs/1524527472", 
        "completed_at": "2020-12-09T14:34:11Z", 
        "run_url": "https://api.github.com/repos/CHChang810716/hunter/actions/runs/410814899", 
        "node_id": "MDg6Q2hlY2tSdW4xNTI0NTI3NDcy", 
        "steps": [
            {
                "status": "completed", 
                "name": "Set up job", 
                "number": 1, 
                "completed_at": "2020-12-09T14:33:56.000Z", 
                "started_at": "2020-12-09T14:33:53.000Z", 
                "conclusion": "success"
            }, 
            {
                "status": "completed", 
                "name": "Git checkout with submodules", 
                "number": 2, 
                "completed_at": "2020-12-09T14:34:00.000Z", 
                "started_at": "2020-12-09T14:33:56.000Z", 
                "conclusion": "success"
            }, 
            {
                "status": "completed", 
                "name": "Set up Python", 
                "number": 3, 
                "completed_at": "2020-12-09T14:34:00.000Z", 
                "started_at": "2020-12-09T14:34:00.000Z", 
                "conclusion": "success"
            }, 
            {
                "status": "completed", 
                "name": "Set up Python environment variable (Unix)", 
                "number": 4, 
                "completed_at": "2020-12-09T14:34:00.000Z", 
                "started_at": "2020-12-09T14:34:00.000Z", 
                "conclusion": "success"
            }, 
            {
                "status": "completed", 
                "name": "Set up Python environment variable (Windows)", 
                "number": 5, 
                "completed_at": "2020-12-09T14:34:00.000Z", 
                "started_at": "2020-12-09T14:34:00.000Z", 
                "conclusion": "skipped"
            }, 
            {
                "status": "completed", 
                "name": "Extract branch name", 
                "number": 6, 
                "completed_at": "2020-12-09T14:34:00.000Z", 
                "started_at": "2020-12-09T14:34:00.000Z", 
                "conclusion": "success"
            }, 
            {
                "status": "completed", 
                "name": "Upgrade pip", 
                "number": 7, 
                "completed_at": "2020-12-09T14:34:04.000Z", 
                "started_at": "2020-12-09T14:34:00.000Z", 
                "conclusion": "success"
            }, 
            {
                "status": "completed", 
                "name": "Build on Unix", 
                "number": 8, 
                "completed_at": "2020-12-09T14:34:11.000Z", 
                "started_at": "2020-12-09T14:34:04.000Z", 
                "conclusion": "failure"
            }, 
            {
                "status": "completed", 
                "name": "Build on Windows", 
                "number": 9, 
                "completed_at": "2020-12-09T14:34:11.000Z", 
                "started_at": "2020-12-09T14:34:11.000Z", 
                "conclusion": "skipped"
            }, 
            {
                "status": "completed", 
                "name": "Post Git checkout with submodules", 
                "number": 18, 
                "completed_at": "2020-12-09T14:34:11.000Z", 
                "started_at": "2020-12-09T14:34:11.000Z", 
                "conclusion": "success"
            }, 
            {
                "status": "completed", 
                "name": "Complete job", 
                "number": 19, 
                "completed_at": "2020-12-09T14:34:11.000Z", 
                "started_at": "2020-12-09T14:34:11.000Z", 
                "conclusion": "success"
            }
        ], 
        "head_sha": "950960e8f1d67f7bc64155417f4a8e8ccebbad64", 
        "started_at": "2020-12-09T14:33:53Z", 
        "id": 1524527472, 
        "conclusion": "failure"
    }, 
    {
        "status": "completed", 
        "check_run_url": "https://api.github.com/repos/CHChang810716/hunter/check-runs/1524527503", 
        "name": "Arkitekto gcc-7-cxx17 ubuntu-16.04", 
        "run_id": 410814899, 
        "url": "https://api.github.com/repos/CHChang810716/hunter/actions/jobs/1524527503", 
        "html_url": "https://github.com/CHChang810716/hunter/runs/1524527503", 
        "completed_at": "2020-12-09T14:34:05Z", 
        "run_url": "https://api.github.com/repos/CHChang810716/hunter/actions/runs/410814899", 
        "node_id": "MDg6Q2hlY2tSdW4xNTI0NTI3NTAz", 
        "steps": [
            {
                "status": "completed", 
                "name": "Set up job", 
                "number": 1, 
                "completed_at": "2020-12-09T14:33:55.000Z", 
                "started_at": "2020-12-09T14:33:52.000Z", 
                "conclusion": "success"
            }, 
            {
                "status": "completed", 
                "name": "Git checkout with submodules", 
                "number": 2, 
                "completed_at": "2020-12-09T14:33:58.000Z", 
                "started_at": "2020-12-09T14:33:55.000Z", 
                "conclusion": "success"
            }, 
            {
                "status": "completed", 
                "name": "Set up Python", 
                "number": 3, 
                "completed_at": "2020-12-09T14:33:58.000Z", 
                "started_at": "2020-12-09T14:33:58.000Z", 
                "conclusion": "success"
            }, 
            {
                "status": "completed", 
                "name": "Set up Python environment variable (Unix)", 
                "number": 4, 
                "completed_at": "2020-12-09T14:33:58.000Z", 
                "started_at": "2020-12-09T14:33:58.000Z", 
                "conclusion": "success"
            }, 
            {
                "status": "completed", 
                "name": "Set up Python environment variable (Windows)", 
                "number": 5, 
                "completed_at": "2020-12-09T14:33:58.000Z", 
                "started_at": "2020-12-09T14:33:58.000Z", 
                "conclusion": "skipped"
            }, 
            {
                "status": "completed", 
                "name": "Extract branch name", 
                "number": 6, 
                "completed_at": "2020-12-09T14:33:58.000Z", 
                "started_at": "2020-12-09T14:33:58.000Z", 
                "conclusion": "success"
            }, 
            {
                "status": "completed", 
                "name": "Upgrade pip", 
                "number": 7, 
                "completed_at": "2020-12-09T14:34:00.000Z", 
                "started_at": "2020-12-09T14:33:58.000Z", 
                "conclusion": "success"
            }, 
            {
                "status": "completed", 
                "name": "Build on Unix", 
                "number": 8, 
                "completed_at": "2020-12-09T14:34:05.000Z", 
                "started_at": "2020-12-09T14:34:00.000Z", 
                "conclusion": "failure"
            }, 
            {
                "status": "completed", 
                "name": "Build on Windows", 
                "number": 9, 
                "completed_at": "2020-12-09T14:34:05.000Z", 
                "started_at": "2020-12-09T14:34:05.000Z", 
                "conclusion": "skipped"
            }, 
            {
                "status": "completed", 
                "name": "Post Git checkout with submodules", 
                "number": 18, 
                "completed_at": "2020-12-09T14:34:05.000Z", 
                "started_at": "2020-12-09T14:34:05.000Z", 
                "conclusion": "success"
            }, 
            {
                "status": "completed", 
                "name": "Complete job", 
                "number": 19, 
                "completed_at": "2020-12-09T14:34:05.000Z", 
                "started_at": "2020-12-09T14:34:05.000Z", 
                "conclusion": "success"
            }
        ], 
        "head_sha": "950960e8f1d67f7bc64155417f4a8e8ccebbad64", 
        "started_at": "2020-12-09T14:33:52Z", 
        "id": 1524527503, 
        "conclusion": "failure"
    }, 
    {
        "status": "completed", 
        "check_run_url": "https://api.github.com/repos/CHChang810716/hunter/check-runs/1524527523", 
        "name": "Arkitekto gcc-8-cxx17-fpic ubuntu-18.04", 
        "run_id": 410814899, 
        "url": "https://api.github.com/repos/CHChang810716/hunter/actions/jobs/1524527523", 
        "html_url": "https://github.com/CHChang810716/hunter/runs/1524527523", 
        "completed_at": "2020-12-09T14:34:27Z", 
        "run_url": "https://api.github.com/repos/CHChang810716/hunter/actions/runs/410814899", 
        "node_id": "MDg6Q2hlY2tSdW4xNTI0NTI3NTIz", 
        "steps": [
            {
                "status": "completed", 
                "name": "Set up job", 
                "number": 1, 
                "completed_at": "2020-12-09T14:34:08.000Z", 
                "started_at": "2020-12-09T14:34:02.000Z", 
                "conclusion": "success"
            }, 
            {
                "status": "completed", 
                "name": "Git checkout with submodules", 
                "number": 2, 
                "completed_at": "2020-12-09T14:34:15.000Z", 
                "started_at": "2020-12-09T14:34:08.000Z", 
                "conclusion": "success"
            }, 
            {
                "status": "completed", 
                "name": "Set up Python", 
                "number": 3, 
                "completed_at": "2020-12-09T14:34:15.000Z", 
                "started_at": "2020-12-09T14:34:15.000Z", 
                "conclusion": "success"
            }, 
            {
                "status": "completed", 
                "name": "Set up Python environment variable (Unix)", 
                "number": 4, 
                "completed_at": "2020-12-09T14:34:15.000Z", 
                "started_at": "2020-12-09T14:34:15.000Z", 
                "conclusion": "success"
            }, 
            {
                "status": "completed", 
                "name": "Set up Python environment variable (Windows)", 
                "number": 5, 
                "completed_at": "2020-12-09T14:34:15.000Z", 
                "started_at": "2020-12-09T14:34:15.000Z", 
                "conclusion": "skipped"
            }, 
            {
                "status": "completed", 
                "name": "Extract branch name", 
                "number": 6, 
                "completed_at": "2020-12-09T14:34:15.000Z", 
                "started_at": "2020-12-09T14:34:15.000Z", 
                "conclusion": "success"
            }, 
            {
                "status": "completed", 
                "name": "Upgrade pip", 
                "number": 7, 
                "completed_at": "2020-12-09T14:34:18.000Z", 
                "started_at": "2020-12-09T14:34:15.000Z", 
                "conclusion": "success"
            }, 
            {
                "status": "completed", 
                "name": "Build on Unix", 
                "number": 8, 
                "completed_at": "2020-12-09T14:34:27.000Z", 
                "started_at": "2020-12-09T14:34:18.000Z", 
                "conclusion": "failure"
            }, 
            {
                "status": "completed", 
                "name": "Build on Windows", 
                "number": 9, 
                "completed_at": "2020-12-09T14:34:27.000Z", 
                "started_at": "2020-12-09T14:34:27.000Z", 
                "conclusion": "skipped"
            }, 
            {
                "status": "completed", 
                "name": "Post Git checkout with submodules", 
                "number": 18, 
                "completed_at": "2020-12-09T14:34:27.000Z", 
                "started_at": "2020-12-09T14:34:27.000Z", 
                "conclusion": "success"
            }, 
            {
                "status": "completed", 
                "name": "Complete job", 
                "number": 19, 
                "completed_at": "2020-12-09T14:34:27.000Z", 
                "started_at": "2020-12-09T14:34:27.000Z", 
                "conclusion": "success"
            }
        ], 
        "head_sha": "950960e8f1d67f7bc64155417f4a8e8ccebbad64", 
        "started_at": "2020-12-09T14:34:02Z", 
        "id": 1524527523, 
        "conclusion": "failure"
    }, 
    {
        "status": "completed", 
        "check_run_url": "https://api.github.com/repos/CHChang810716/hunter/check-runs/1524527547", 
        "name": "Arkitekto gcc-9-cxx17-fpic ubuntu-20.04", 
        "run_id": 410814899, 
        "url": "https://api.github.com/repos/CHChang810716/hunter/actions/jobs/1524527547", 
        "html_url": "https://github.com/CHChang810716/hunter/runs/1524527547", 
        "completed_at": "2020-12-09T14:34:20Z", 
        "run_url": "https://api.github.com/repos/CHChang810716/hunter/actions/runs/410814899", 
        "node_id": "MDg6Q2hlY2tSdW4xNTI0NTI3NTQ3", 
        "steps": [
            {
                "status": "completed", 
                "name": "Set up job", 
                "number": 1, 
                "completed_at": "2020-12-09T14:33:57.000Z", 
                "started_at": "2020-12-09T14:33:54.000Z", 
                "conclusion": "success"
            }, 
            {
                "status": "completed", 
                "name": "Git checkout with submodules", 
                "number": 2, 
                "completed_at": "2020-12-09T14:34:05.000Z", 
                "started_at": "2020-12-09T14:33:57.000Z", 
                "conclusion": "success"
            }, 
            {
                "status": "completed", 
                "name": "Set up Python", 
                "number": 3, 
                "completed_at": "2020-12-09T14:34:05.000Z", 
                "started_at": "2020-12-09T14:34:05.000Z", 
                "conclusion": "success"
            }, 
            {
                "status": "completed", 
                "name": "Set up Python environment variable (Unix)", 
                "number": 4, 
                "completed_at": "2020-12-09T14:34:05.000Z", 
                "started_at": "2020-12-09T14:34:05.000Z", 
                "conclusion": "success"
            }, 
            {
                "status": "completed", 
                "name": "Set up Python environment variable (Windows)", 
                "number": 5, 
                "completed_at": "2020-12-09T14:34:05.000Z", 
                "started_at": "2020-12-09T14:34:05.000Z", 
                "conclusion": "skipped"
            }, 
            {
                "status": "completed", 
                "name": "Extract branch name", 
                "number": 6, 
                "completed_at": "2020-12-09T14:34:05.000Z", 
                "started_at": "2020-12-09T14:34:05.000Z", 
                "conclusion": "success"
            }, 
            {
                "status": "completed", 
                "name": "Upgrade pip", 
                "number": 7, 
                "completed_at": "2020-12-09T14:34:11.000Z", 
                "started_at": "2020-12-09T14:34:05.000Z", 
                "conclusion": "success"
            }, 
            {
                "status": "completed", 
                "name": "Build on Unix", 
                "number": 8, 
                "completed_at": "2020-12-09T14:34:20.000Z", 
                "started_at": "2020-12-09T14:34:11.000Z", 
                "conclusion": "failure"
            }, 
            {
                "status": "completed", 
                "name": "Build on Windows", 
                "number": 9, 
                "completed_at": "2020-12-09T14:34:20.000Z", 
                "started_at": "2020-12-09T14:34:20.000Z", 
                "conclusion": "skipped"
            }, 
            {
                "status": "completed", 
                "name": "Post Git checkout with submodules", 
                "number": 18, 
                "completed_at": "2020-12-09T14:34:20.000Z", 
                "started_at": "2020-12-09T14:34:20.000Z", 
                "conclusion": "success"
            }, 
            {
                "status": "completed", 
                "name": "Complete job", 
                "number": 19, 
                "completed_at": "2020-12-09T14:34:20.000Z", 
                "started_at": "2020-12-09T14:34:20.000Z", 
                "conclusion": "success"
            }
        ], 
        "head_sha": "950960e8f1d67f7bc64155417f4a8e8ccebbad64", 
        "started_at": "2020-12-09T14:33:54Z", 
        "id": 1524527547, 
        "conclusion": "failure"
    }, 
    {
        "status": "completed", 
        "check_run_url": "https://api.github.com/repos/CHChang810716/hunter/check-runs/1524527741", 
        "name": "Arkitekto ios-nocodesign-13-2-dep-9-3 macos-10.15", 
        "run_id": 410814899, 
        "url": "https://api.github.com/repos/CHChang810716/hunter/actions/jobs/1524527741", 
        "html_url": "https://github.com/CHChang810716/hunter/runs/1524527741", 
        "completed_at": "2020-12-09T14:34:28Z", 
        "run_url": "https://api.github.com/repos/CHChang810716/hunter/actions/runs/410814899", 
        "node_id": "MDg6Q2hlY2tSdW4xNTI0NTI3NzQx", 
        "steps": [
            {
                "status": "completed", 
                "name": "Set up job", 
                "number": 1, 
                "completed_at": "2020-12-09T14:34:05.000Z", 
                "started_at": "2020-12-09T14:34:04.000Z", 
                "conclusion": "success"
            }, 
            {
                "status": "completed", 
                "name": "Git checkout with submodules", 
                "number": 2, 
                "completed_at": "2020-12-09T14:34:13.000Z", 
                "started_at": "2020-12-09T14:34:05.000Z", 
                "conclusion": "success"
            }, 
            {
                "status": "completed", 
                "name": "Set up Python", 
                "number": 3, 
                "completed_at": "2020-12-09T14:34:13.000Z", 
                "started_at": "2020-12-09T14:34:13.000Z", 
                "conclusion": "success"
            }, 
            {
                "status": "completed", 
                "name": "Set up Python environment variable (Unix)", 
                "number": 4, 
                "completed_at": "2020-12-09T14:34:13.000Z", 
                "started_at": "2020-12-09T14:34:13.000Z", 
                "conclusion": "success"
            }, 
            {
                "status": "completed", 
                "name": "Set up Python environment variable (Windows)", 
                "number": 5, 
                "completed_at": "2020-12-09T14:34:13.000Z", 
                "started_at": "2020-12-09T14:34:13.000Z", 
                "conclusion": "skipped"
            }, 
            {
                "status": "completed", 
                "name": "Extract branch name", 
                "number": 6, 
                "completed_at": "2020-12-09T14:34:13.000Z", 
                "started_at": "2020-12-09T14:34:13.000Z", 
                "conclusion": "success"
            }, 
            {
                "status": "completed", 
                "name": "Upgrade pip", 
                "number": 7, 
                "completed_at": "2020-12-09T14:34:18.000Z", 
                "started_at": "2020-12-09T14:34:13.000Z", 
                "conclusion": "success"
            }, 
            {
                "status": "completed", 
                "name": "Build on Unix", 
                "number": 8, 
                "completed_at": "2020-12-09T14:34:27.000Z", 
                "started_at": "2020-12-09T14:34:18.000Z", 
                "conclusion": "failure"
            }, 
            {
                "status": "completed", 
                "name": "Build on Windows", 
                "number": 9, 
                "completed_at": "2020-12-09T14:34:27.000Z", 
                "started_at": "2020-12-09T14:34:27.000Z", 
                "conclusion": "skipped"
            }, 
            {
                "status": "completed", 
                "name": "Post Git checkout with submodules", 
                "number": 18, 
                "completed_at": "2020-12-09T14:34:28.000Z", 
                "started_at": "2020-12-09T14:34:27.000Z", 
                "conclusion": "success"
            }, 
            {
                "status": "completed", 
                "name": "Complete job", 
                "number": 19, 
                "completed_at": "2020-12-09T14:34:28.000Z", 
                "started_at": "2020-12-09T14:34:28.000Z", 
                "conclusion": "success"
            }
        ], 
        "head_sha": "950960e8f1d67f7bc64155417f4a8e8ccebbad64", 
        "started_at": "2020-12-09T14:34:04Z", 
        "id": 1524527741, 
        "conclusion": "failure"
    }, 
    {
        "status": "completed", 
        "check_run_url": "https://api.github.com/repos/CHChang810716/hunter/check-runs/1524527849", 
        "name": "Arkitekto mingw-cxx17 windows-2016", 
        "run_id": 410814899, 
        "url": "https://api.github.com/repos/CHChang810716/hunter/actions/jobs/1524527849", 
        "html_url": "https://github.com/CHChang810716/hunter/runs/1524527849", 
        "completed_at": "2020-12-09T14:34:42Z", 
        "run_url": "https://api.github.com/repos/CHChang810716/hunter/actions/runs/410814899", 
        "node_id": "MDg6Q2hlY2tSdW4xNTI0NTI3ODQ5", 
        "steps": [
            {
                "status": "completed", 
                "name": "Set up job", 
                "number": 1, 
                "completed_at": "2020-12-09T14:33:57.000Z", 
                "started_at": "2020-12-09T14:33:54.000Z", 
                "conclusion": "success"
            }, 
            {
                "status": "completed", 
                "name": "Git checkout with submodules", 
                "number": 2, 
                "completed_at": "2020-12-09T14:34:12.000Z", 
                "started_at": "2020-12-09T14:33:57.000Z", 
                "conclusion": "success"
            }, 
            {
                "status": "completed", 
                "name": "Set up Python", 
                "number": 3, 
                "completed_at": "2020-12-09T14:34:12.000Z", 
                "started_at": "2020-12-09T14:34:12.000Z", 
                "conclusion": "success"
            }, 
            {
                "status": "completed", 
                "name": "Set up Python environment variable (Unix)", 
                "number": 4, 
                "completed_at": "2020-12-09T14:34:12.000Z", 
                "started_at": "2020-12-09T14:34:12.000Z", 
                "conclusion": "skipped"
            }, 
            {
                "status": "completed", 
                "name": "Set up Python environment variable (Windows)", 
                "number": 5, 
                "completed_at": "2020-12-09T14:34:13.000Z", 
                "started_at": "2020-12-09T14:34:12.000Z", 
                "conclusion": "success"
            }, 
            {
                "status": "completed", 
                "name": "Extract branch name", 
                "number": 6, 
                "completed_at": "2020-12-09T14:34:13.000Z", 
                "started_at": "2020-12-09T14:34:13.000Z", 
                "conclusion": "success"
            }, 
            {
                "status": "completed", 
                "name": "Upgrade pip", 
                "number": 7, 
                "completed_at": "2020-12-09T14:34:21.000Z", 
                "started_at": "2020-12-09T14:34:13.000Z", 
                "conclusion": "success"
            }, 
            {
                "status": "completed", 
                "name": "Build on Unix", 
                "number": 8, 
                "completed_at": "2020-12-09T14:34:21.000Z", 
                "started_at": "2020-12-09T14:34:21.000Z", 
                "conclusion": "skipped"
            }, 
            {
                "status": "completed", 
                "name": "Build on Windows", 
                "number": 9, 
                "completed_at": "2020-12-09T14:34:38.000Z", 
                "started_at": "2020-12-09T14:34:21.000Z", 
                "conclusion": "failure"
            }, 
            {
                "status": "completed", 
                "name": "Post Git checkout with submodules", 
                "number": 18, 
                "completed_at": "2020-12-09T14:34:42.000Z", 
                "started_at": "2020-12-09T14:34:38.000Z", 
                "conclusion": "success"
            }, 
            {
                "status": "completed", 
                "name": "Complete job", 
                "number": 19, 
                "completed_at": "2020-12-09T14:34:42.000Z", 
                "started_at": "2020-12-09T14:34:42.000Z", 
                "conclusion": "success"
            }
        ], 
        "head_sha": "950960e8f1d67f7bc64155417f4a8e8ccebbad64", 
        "started_at": "2020-12-09T14:33:54Z", 
        "id": 1524527849, 
        "conclusion": "failure"
    }, 
    {
        "status": "completed", 
        "check_run_url": "https://api.github.com/repos/CHChang810716/hunter/check-runs/1524527879", 
        "name": "Arkitekto msys-cxx17 windows-2016", 
        "run_id": 410814899, 
        "url": "https://api.github.com/repos/CHChang810716/hunter/actions/jobs/1524527879", 
        "html_url": "https://github.com/CHChang810716/hunter/runs/1524527879", 
        "completed_at": "2020-12-09T14:34:41Z", 
        "run_url": "https://api.github.com/repos/CHChang810716/hunter/actions/runs/410814899", 
        "node_id": "MDg6Q2hlY2tSdW4xNTI0NTI3ODc5", 
        "steps": [
            {
                "status": "completed", 
                "name": "Set up job", 
                "number": 1, 
                "completed_at": "2020-12-09T14:33:57.000Z", 
                "started_at": "2020-12-09T14:33:53.000Z", 
                "conclusion": "success"
            }, 
            {
                "status": "completed", 
                "name": "Git checkout with submodules", 
                "number": 2, 
                "completed_at": "2020-12-09T14:34:11.000Z", 
                "started_at": "2020-12-09T14:33:57.000Z", 
                "conclusion": "success"
            }, 
            {
                "status": "completed", 
                "name": "Set up Python", 
                "number": 3, 
                "completed_at": "2020-12-09T14:34:11.000Z", 
                "started_at": "2020-12-09T14:34:11.000Z", 
                "conclusion": "success"
            }, 
            {
                "status": "completed", 
                "name": "Set up Python environment variable (Unix)", 
                "number": 4, 
                "completed_at": "2020-12-09T14:34:11.000Z", 
                "started_at": "2020-12-09T14:34:11.000Z", 
                "conclusion": "skipped"
            }, 
            {
                "status": "completed", 
                "name": "Set up Python environment variable (Windows)", 
                "number": 5, 
                "completed_at": "2020-12-09T14:34:12.000Z", 
                "started_at": "2020-12-09T14:34:11.000Z", 
                "conclusion": "success"
            }, 
            {
                "status": "completed", 
                "name": "Extract branch name", 
                "number": 6, 
                "completed_at": "2020-12-09T14:34:13.000Z", 
                "started_at": "2020-12-09T14:34:12.000Z", 
                "conclusion": "success"
            }, 
            {
                "status": "completed", 
                "name": "Upgrade pip", 
                "number": 7, 
                "completed_at": "2020-12-09T14:34:21.000Z", 
                "started_at": "2020-12-09T14:34:13.000Z", 
                "conclusion": "success"
            }, 
            {
                "status": "completed", 
                "name": "Build on Unix", 
                "number": 8, 
                "completed_at": "2020-12-09T14:34:21.000Z", 
                "started_at": "2020-12-09T14:34:21.000Z", 
                "conclusion": "skipped"
            }, 
            {
                "status": "completed", 
                "name": "Build on Windows", 
                "number": 9, 
                "completed_at": "2020-12-09T14:34:38.000Z", 
                "started_at": "2020-12-09T14:34:21.000Z", 
                "conclusion": "failure"
            }, 
            {
                "status": "completed", 
                "name": "Post Git checkout with submodules", 
                "number": 18, 
                "completed_at": "2020-12-09T14:34:41.000Z", 
                "started_at": "2020-12-09T14:34:38.000Z", 
                "conclusion": "success"
            }, 
            {
                "status": "completed", 
                "name": "Complete job", 
                "number": 19, 
                "completed_at": "2020-12-09T14:34:41.000Z", 
                "started_at": "2020-12-09T14:34:41.000Z", 
                "conclusion": "success"
            }
        ], 
        "head_sha": "950960e8f1d67f7bc64155417f4a8e8ccebbad64", 
        "started_at": "2020-12-09T14:33:53Z", 
        "id": 1524527879, 
        "conclusion": "failure"
    }, 
    {
        "status": "completed", 
        "check_run_url": "https://api.github.com/repos/CHChang810716/hunter/check-runs/1524527758", 
        "name": "Arkitekto ninja-vs-15-2017-win64-cxx17 windows-2016", 
        "run_id": 410814899, 
        "url": "https://api.github.com/repos/CHChang810716/hunter/actions/jobs/1524527758", 
        "html_url": "https://github.com/CHChang810716/hunter/runs/1524527758", 
        "completed_at": "2020-12-09T14:34:39Z", 
        "run_url": "https://api.github.com/repos/CHChang810716/hunter/actions/runs/410814899", 
        "node_id": "MDg6Q2hlY2tSdW4xNTI0NTI3NzU4", 
        "steps": [
            {
                "status": "completed", 
                "name": "Set up job", 
                "number": 1, 
                "completed_at": "2020-12-09T14:33:55.000Z", 
                "started_at": "2020-12-09T14:33:52.000Z", 
                "conclusion": "success"
            }, 
            {
                "status": "completed", 
                "name": "Git checkout with submodules", 
                "number": 2, 
                "completed_at": "2020-12-09T14:34:09.000Z", 
                "started_at": "2020-12-09T14:33:55.000Z", 
                "conclusion": "success"
            }, 
            {
                "status": "completed", 
                "name": "Set up Python", 
                "number": 3, 
                "completed_at": "2020-12-09T14:34:09.000Z", 
                "started_at": "2020-12-09T14:34:09.000Z", 
                "conclusion": "success"
            }, 
            {
                "status": "completed", 
                "name": "Set up Python environment variable (Unix)", 
                "number": 4, 
                "completed_at": "2020-12-09T14:34:09.000Z", 
                "started_at": "2020-12-09T14:34:09.000Z", 
                "conclusion": "skipped"
            }, 
            {
                "status": "completed", 
                "name": "Set up Python environment variable (Windows)", 
                "number": 5, 
                "completed_at": "2020-12-09T14:34:10.000Z", 
                "started_at": "2020-12-09T14:34:09.000Z", 
                "conclusion": "success"
            }, 
            {
                "status": "completed", 
                "name": "Extract branch name", 
                "number": 6, 
                "completed_at": "2020-12-09T14:34:10.000Z", 
                "started_at": "2020-12-09T14:34:10.000Z", 
                "conclusion": "success"
            }, 
            {
                "status": "completed", 
                "name": "Upgrade pip", 
                "number": 7, 
                "completed_at": "2020-12-09T14:34:17.000Z", 
                "started_at": "2020-12-09T14:34:10.000Z", 
                "conclusion": "success"
            }, 
            {
                "status": "completed", 
                "name": "Build on Unix", 
                "number": 8, 
                "completed_at": "2020-12-09T14:34:17.000Z", 
                "started_at": "2020-12-09T14:34:17.000Z", 
                "conclusion": "skipped"
            }, 
            {
                "status": "completed", 
                "name": "Build on Windows", 
                "number": 9, 
                "completed_at": "2020-12-09T14:34:36.000Z", 
                "started_at": "2020-12-09T14:34:17.000Z", 
                "conclusion": "failure"
            }, 
            {
                "status": "completed", 
                "name": "Post Git checkout with submodules", 
                "number": 18, 
                "completed_at": "2020-12-09T14:34:39.000Z", 
                "started_at": "2020-12-09T14:34:36.000Z", 
                "conclusion": "success"
            }, 
            {
                "status": "completed", 
                "name": "Complete job", 
                "number": 19, 
                "completed_at": "2020-12-09T14:34:39.000Z", 
                "started_at": "2020-12-09T14:34:39.000Z", 
                "conclusion": "success"
            }
        ], 
        "head_sha": "950960e8f1d67f7bc64155417f4a8e8ccebbad64", 
        "started_at": "2020-12-09T14:33:52Z", 
        "id": 1524527758, 
        "conclusion": "failure"
    }, 
    {
        "status": "completed", 
        "check_run_url": "https://api.github.com/repos/CHChang810716/hunter/check-runs/1524527778", 
        "name": "Arkitekto nmake-vs-15-2017-win64-cxx17 windows-2016", 
        "run_id": 410814899, 
        "url": "https://api.github.com/repos/CHChang810716/hunter/actions/jobs/1524527778", 
        "html_url": "https://github.com/CHChang810716/hunter/runs/1524527778", 
        "completed_at": "2020-12-09T14:34:45Z", 
        "run_url": "https://api.github.com/repos/CHChang810716/hunter/actions/runs/410814899", 
        "node_id": "MDg6Q2hlY2tSdW4xNTI0NTI3Nzc4", 
        "steps": [
            {
                "status": "completed", 
                "name": "Set up job", 
                "number": 1, 
                "completed_at": "2020-12-09T14:33:57.000Z", 
                "started_at": "2020-12-09T14:33:54.000Z", 
                "conclusion": "success"
            }, 
            {
                "status": "completed", 
                "name": "Git checkout with submodules", 
                "number": 2, 
                "completed_at": "2020-12-09T14:34:12.000Z", 
                "started_at": "2020-12-09T14:33:57.000Z", 
                "conclusion": "success"
            }, 
            {
                "status": "completed", 
                "name": "Set up Python", 
                "number": 3, 
                "completed_at": "2020-12-09T14:34:12.000Z", 
                "started_at": "2020-12-09T14:34:12.000Z", 
                "conclusion": "success"
            }, 
            {
                "status": "completed", 
                "name": "Set up Python environment variable (Unix)", 
                "number": 4, 
                "completed_at": "2020-12-09T14:34:12.000Z", 
                "started_at": "2020-12-09T14:34:12.000Z", 
                "conclusion": "skipped"
            }, 
            {
                "status": "completed", 
                "name": "Set up Python environment variable (Windows)", 
                "number": 5, 
                "completed_at": "2020-12-09T14:34:13.000Z", 
                "started_at": "2020-12-09T14:34:12.000Z", 
                "conclusion": "success"
            }, 
            {
                "status": "completed", 
                "name": "Extract branch name", 
                "number": 6, 
                "completed_at": "2020-12-09T14:34:13.000Z", 
                "started_at": "2020-12-09T14:34:13.000Z", 
                "conclusion": "success"
            }, 
            {
                "status": "completed", 
                "name": "Upgrade pip", 
                "number": 7, 
                "completed_at": "2020-12-09T14:34:22.000Z", 
                "started_at": "2020-12-09T14:34:13.000Z", 
                "conclusion": "success"
            }, 
            {
                "status": "completed", 
                "name": "Build on Unix", 
                "number": 8, 
                "completed_at": "2020-12-09T14:34:22.000Z", 
                "started_at": "2020-12-09T14:34:22.000Z", 
                "conclusion": "skipped"
            }, 
            {
                "status": "completed", 
                "name": "Build on Windows", 
                "number": 9, 
                "completed_at": "2020-12-09T14:34:41.000Z", 
                "started_at": "2020-12-09T14:34:22.000Z", 
                "conclusion": "failure"
            }, 
            {
                "status": "completed", 
                "name": "Post Git checkout with submodules", 
                "number": 18, 
                "completed_at": "2020-12-09T14:34:44.000Z", 
                "started_at": "2020-12-09T14:34:41.000Z", 
                "conclusion": "success"
            }, 
            {
                "status": "completed", 
                "name": "Complete job", 
                "number": 19, 
                "completed_at": "2020-12-09T14:34:45.000Z", 
                "started_at": "2020-12-09T14:34:44.000Z", 
                "conclusion": "success"
            }
        ], 
        "head_sha": "950960e8f1d67f7bc64155417f4a8e8ccebbad64", 
        "started_at": "2020-12-09T14:33:54Z", 
        "id": 1524527778, 
        "conclusion": "failure"
    }, 
    {
        "status": "completed", 
        "check_run_url": "https://api.github.com/repos/CHChang810716/hunter/check-runs/1524527690", 
        "name": "Arkitekto osx-10-13-cxx14 macos-10.15", 
        "run_id": 410814899, 
        "url": "https://api.github.com/repos/CHChang810716/hunter/actions/jobs/1524527690", 
        "html_url": "https://github.com/CHChang810716/hunter/runs/1524527690", 
        "completed_at": "2020-12-09T14:34:45Z", 
        "run_url": "https://api.github.com/repos/CHChang810716/hunter/actions/runs/410814899", 
        "node_id": "MDg6Q2hlY2tSdW4xNTI0NTI3Njkw", 
        "steps": [
            {
                "status": "completed", 
                "name": "Set up job", 
                "number": 1, 
                "completed_at": "2020-12-09T14:34:22.000Z", 
                "started_at": "2020-12-09T14:34:13.000Z", 
                "conclusion": "success"
            }, 
            {
                "status": "completed", 
                "name": "Git checkout with submodules", 
                "number": 2, 
                "completed_at": "2020-12-09T14:34:33.000Z", 
                "started_at": "2020-12-09T14:34:22.000Z", 
                "conclusion": "success"
            }, 
            {
                "status": "completed", 
                "name": "Set up Python", 
                "number": 3, 
                "completed_at": "2020-12-09T14:34:33.000Z", 
                "started_at": "2020-12-09T14:34:33.000Z", 
                "conclusion": "success"
            }, 
            {
                "status": "completed", 
                "name": "Set up Python environment variable (Unix)", 
                "number": 4, 
                "completed_at": "2020-12-09T14:34:33.000Z", 
                "started_at": "2020-12-09T14:34:33.000Z", 
                "conclusion": "success"
            }, 
            {
                "status": "completed", 
                "name": "Set up Python environment variable (Windows)", 
                "number": 5, 
                "completed_at": "2020-12-09T14:34:33.000Z", 
                "started_at": "2020-12-09T14:34:33.000Z", 
                "conclusion": "skipped"
            }, 
            {
                "status": "completed", 
                "name": "Extract branch name", 
                "number": 6, 
                "completed_at": "2020-12-09T14:34:33.000Z", 
                "started_at": "2020-12-09T14:34:33.000Z", 
                "conclusion": "success"
            }, 
            {
                "status": "completed", 
                "name": "Upgrade pip", 
                "number": 7, 
                "completed_at": "2020-12-09T14:34:37.000Z", 
                "started_at": "2020-12-09T14:34:33.000Z", 
                "conclusion": "success"
            }, 
            {
                "status": "completed", 
                "name": "Build on Unix", 
                "number": 8, 
                "completed_at": "2020-12-09T14:34:45.000Z", 
                "started_at": "2020-12-09T14:34:37.000Z", 
                "conclusion": "failure"
            }, 
            {
                "status": "completed", 
                "name": "Build on Windows", 
                "number": 9, 
                "completed_at": "2020-12-09T14:34:45.000Z", 
                "started_at": "2020-12-09T14:34:45.000Z", 
                "conclusion": "skipped"
            }, 
            {
                "status": "completed", 
                "name": "Post Git checkout with submodules", 
                "number": 18, 
                "completed_at": "2020-12-09T14:34:45.000Z", 
                "started_at": "2020-12-09T14:34:45.000Z", 
                "conclusion": "success"
            }, 
            {
                "status": "completed", 
                "name": "Complete job", 
                "number": 19, 
                "completed_at": "2020-12-09T14:34:45.000Z", 
                "started_at": "2020-12-09T14:34:45.000Z", 
                "conclusion": "success"
            }
        ], 
        "head_sha": "950960e8f1d67f7bc64155417f4a8e8ccebbad64", 
        "started_at": "2020-12-09T14:34:13Z", 
        "id": 1524527690, 
        "conclusion": "failure"
    }, 
    {
        "status": "completed", 
        "check_run_url": "https://api.github.com/repos/CHChang810716/hunter/check-runs/1524527672", 
        "name": "Arkitekto osx-10-13-make-cxx14 macos-10.15", 
        "run_id": 410814899, 
        "url": "https://api.github.com/repos/CHChang810716/hunter/actions/jobs/1524527672", 
        "html_url": "https://github.com/CHChang810716/hunter/runs/1524527672", 
        "completed_at": "2020-12-09T14:34:26Z", 
        "run_url": "https://api.github.com/repos/CHChang810716/hunter/actions/runs/410814899", 
        "node_id": "MDg6Q2hlY2tSdW4xNTI0NTI3Njcy", 
        "steps": [
            {
                "status": "completed", 
                "name": "Set up job", 
                "number": 1, 
                "completed_at": "2020-12-09T14:34:05.000Z", 
                "started_at": "2020-12-09T14:34:03.000Z", 
                "conclusion": "success"
            }, 
            {
                "status": "completed", 
                "name": "Git checkout with submodules", 
                "number": 2, 
                "completed_at": "2020-12-09T14:34:11.000Z", 
                "started_at": "2020-12-09T14:34:05.000Z", 
                "conclusion": "success"
            }, 
            {
                "status": "completed", 
                "name": "Set up Python", 
                "number": 3, 
                "completed_at": "2020-12-09T14:34:11.000Z", 
                "started_at": "2020-12-09T14:34:11.000Z", 
                "conclusion": "success"
            }, 
            {
                "status": "completed", 
                "name": "Set up Python environment variable (Unix)", 
                "number": 4, 
                "completed_at": "2020-12-09T14:34:11.000Z", 
                "started_at": "2020-12-09T14:34:11.000Z", 
                "conclusion": "success"
            }, 
            {
                "status": "completed", 
                "name": "Set up Python environment variable (Windows)", 
                "number": 5, 
                "completed_at": "2020-12-09T14:34:11.000Z", 
                "started_at": "2020-12-09T14:34:11.000Z", 
                "conclusion": "skipped"
            }, 
            {
                "status": "completed", 
                "name": "Extract branch name", 
                "number": 6, 
                "completed_at": "2020-12-09T14:34:11.000Z", 
                "started_at": "2020-12-09T14:34:11.000Z", 
                "conclusion": "success"
            }, 
            {
                "status": "completed", 
                "name": "Upgrade pip", 
                "number": 7, 
                "completed_at": "2020-12-09T14:34:17.000Z", 
                "started_at": "2020-12-09T14:34:11.000Z", 
                "conclusion": "success"
            }, 
            {
                "status": "completed", 
                "name": "Build on Unix", 
                "number": 8, 
                "completed_at": "2020-12-09T14:34:25.000Z", 
                "started_at": "2020-12-09T14:34:17.000Z", 
                "conclusion": "failure"
            }, 
            {
                "status": "completed", 
                "name": "Build on Windows", 
                "number": 9, 
                "completed_at": "2020-12-09T14:34:25.000Z", 
                "started_at": "2020-12-09T14:34:25.000Z", 
                "conclusion": "skipped"
            }, 
            {
                "status": "completed", 
                "name": "Post Git checkout with submodules", 
                "number": 18, 
                "completed_at": "2020-12-09T14:34:26.000Z", 
                "started_at": "2020-12-09T14:34:25.000Z", 
                "conclusion": "success"
            }, 
            {
                "status": "completed", 
                "name": "Complete job", 
                "number": 19, 
                "completed_at": "2020-12-09T14:34:26.000Z", 
                "started_at": "2020-12-09T14:34:26.000Z", 
                "conclusion": "success"
            }
        ], 
        "head_sha": "950960e8f1d67f7bc64155417f4a8e8ccebbad64", 
        "started_at": "2020-12-09T14:34:03Z", 
        "id": 1524527672, 
        "conclusion": "failure"
    }, 
    {
        "status": "completed", 
        "check_run_url": "https://api.github.com/repos/CHChang810716/hunter/check-runs/1524527719", 
        "name": "Arkitekto osx-10-15-dep-10-10-cxx17 macos-10.15", 
        "run_id": 410814899, 
        "url": "https://api.github.com/repos/CHChang810716/hunter/actions/jobs/1524527719", 
        "html_url": "https://github.com/CHChang810716/hunter/runs/1524527719", 
        "completed_at": "2020-12-09T14:34:29Z", 
        "run_url": "https://api.github.com/repos/CHChang810716/hunter/actions/runs/410814899", 
        "node_id": "MDg6Q2hlY2tSdW4xNTI0NTI3NzE5", 
        "steps": [
            {
                "status": "completed", 
                "name": "Set up job", 
                "number": 1, 
                "completed_at": "2020-12-09T14:34:03.000Z", 
                "started_at": "2020-12-09T14:34:01.000Z", 
                "conclusion": "success"
            }, 
            {
                "status": "completed", 
                "name": "Git checkout with submodules", 
                "number": 2, 
                "completed_at": "2020-12-09T14:34:11.000Z", 
                "started_at": "2020-12-09T14:34:03.000Z", 
                "conclusion": "success"
            }, 
            {
                "status": "completed", 
                "name": "Set up Python", 
                "number": 3, 
                "completed_at": "2020-12-09T14:34:11.000Z", 
                "started_at": "2020-12-09T14:34:11.000Z", 
                "conclusion": "success"
            }, 
            {
                "status": "completed", 
                "name": "Set up Python environment variable (Unix)", 
                "number": 4, 
                "completed_at": "2020-12-09T14:34:11.000Z", 
                "started_at": "2020-12-09T14:34:11.000Z", 
                "conclusion": "success"
            }, 
            {
                "status": "completed", 
                "name": "Set up Python environment variable (Windows)", 
                "number": 5, 
                "completed_at": "2020-12-09T14:34:11.000Z", 
                "started_at": "2020-12-09T14:34:11.000Z", 
                "conclusion": "skipped"
            }, 
            {
                "status": "completed", 
                "name": "Extract branch name", 
                "number": 6, 
                "completed_at": "2020-12-09T14:34:11.000Z", 
                "started_at": "2020-12-09T14:34:11.000Z", 
                "conclusion": "success"
            }, 
            {
                "status": "completed", 
                "name": "Upgrade pip", 
                "number": 7, 
                "completed_at": "2020-12-09T14:34:17.000Z", 
                "started_at": "2020-12-09T14:34:11.000Z", 
                "conclusion": "success"
            }, 
            {
                "status": "completed", 
                "name": "Build on Unix", 
                "number": 8, 
                "completed_at": "2020-12-09T14:34:28.000Z", 
                "started_at": "2020-12-09T14:34:17.000Z", 
                "conclusion": "failure"
            }, 
            {
                "status": "completed", 
                "name": "Build on Windows", 
                "number": 9, 
                "completed_at": "2020-12-09T14:34:28.000Z", 
                "started_at": "2020-12-09T14:34:28.000Z", 
                "conclusion": "skipped"
            }, 
            {
                "status": "completed", 
                "name": "Post Git checkout with submodules", 
                "number": 18, 
                "completed_at": "2020-12-09T14:34:29.000Z", 
                "started_at": "2020-12-09T14:34:28.000Z", 
                "conclusion": "success"
            }, 
            {
                "status": "completed", 
                "name": "Complete job", 
                "number": 19, 
                "completed_at": "2020-12-09T14:34:29.000Z", 
                "started_at": "2020-12-09T14:34:29.000Z", 
                "conclusion": "success"
            }
        ], 
        "head_sha": "950960e8f1d67f7bc64155417f4a8e8ccebbad64", 
        "started_at": "2020-12-09T14:34:01Z", 
        "id": 1524527719, 
        "conclusion": "failure"
    }, 
    {
        "status": "completed", 
        "check_run_url": "https://api.github.com/repos/CHChang810716/hunter/check-runs/1524527617", 
        "name": "Arkitekto sanitize-address-cxx17 ubuntu-16.04", 
        "run_id": 410814899, 
        "url": "https://api.github.com/repos/CHChang810716/hunter/actions/jobs/1524527617", 
        "html_url": "https://github.com/CHChang810716/hunter/runs/1524527617", 
        "completed_at": "2020-12-09T14:34:14Z", 
        "run_url": "https://api.github.com/repos/CHChang810716/hunter/actions/runs/410814899", 
        "node_id": "MDg6Q2hlY2tSdW4xNTI0NTI3NjE3", 
        "steps": [
            {
                "status": "completed", 
                "name": "Set up job", 
                "number": 1, 
                "completed_at": "2020-12-09T14:33:59.000Z", 
                "started_at": "2020-12-09T14:33:55.000Z", 
                "conclusion": "success"
            }, 
            {
                "status": "completed", 
                "name": "Git checkout with submodules", 
                "number": 2, 
                "completed_at": "2020-12-09T14:34:03.000Z", 
                "started_at": "2020-12-09T14:33:59.000Z", 
                "conclusion": "success"
            }, 
            {
                "status": "completed", 
                "name": "Set up Python", 
                "number": 3, 
                "completed_at": "2020-12-09T14:34:03.000Z", 
                "started_at": "2020-12-09T14:34:03.000Z", 
                "conclusion": "success"
            }, 
            {
                "status": "completed", 
                "name": "Set up Python environment variable (Unix)", 
                "number": 4, 
                "completed_at": "2020-12-09T14:34:03.000Z", 
                "started_at": "2020-12-09T14:34:03.000Z", 
                "conclusion": "success"
            }, 
            {
                "status": "completed", 
                "name": "Set up Python environment variable (Windows)", 
                "number": 5, 
                "completed_at": "2020-12-09T14:34:03.000Z", 
                "started_at": "2020-12-09T14:34:03.000Z", 
                "conclusion": "skipped"
            }, 
            {
                "status": "completed", 
                "name": "Extract branch name", 
                "number": 6, 
                "completed_at": "2020-12-09T14:34:03.000Z", 
                "started_at": "2020-12-09T14:34:03.000Z", 
                "conclusion": "success"
            }, 
            {
                "status": "completed", 
                "name": "Upgrade pip", 
                "number": 7, 
                "completed_at": "2020-12-09T14:34:07.000Z", 
                "started_at": "2020-12-09T14:34:03.000Z", 
                "conclusion": "success"
            }, 
            {
                "status": "completed", 
                "name": "Build on Unix", 
                "number": 8, 
                "completed_at": "2020-12-09T14:34:14.000Z", 
                "started_at": "2020-12-09T14:34:07.000Z", 
                "conclusion": "failure"
            }, 
            {
                "status": "completed", 
                "name": "Build on Windows", 
                "number": 9, 
                "completed_at": "2020-12-09T14:34:14.000Z", 
                "started_at": "2020-12-09T14:34:14.000Z", 
                "conclusion": "skipped"
            }, 
            {
                "status": "completed", 
                "name": "Post Git checkout with submodules", 
                "number": 18, 
                "completed_at": "2020-12-09T14:34:14.000Z", 
                "started_at": "2020-12-09T14:34:14.000Z", 
                "conclusion": "success"
            }, 
            {
                "status": "completed", 
                "name": "Complete job", 
                "number": 19, 
                "completed_at": "2020-12-09T14:34:14.000Z", 
                "started_at": "2020-12-09T14:34:14.000Z", 
                "conclusion": "success"
            }
        ], 
        "head_sha": "950960e8f1d67f7bc64155417f4a8e8ccebbad64", 
        "started_at": "2020-12-09T14:33:55Z", 
        "id": 1524527617, 
        "conclusion": "failure"
    }, 
    {
        "status": "completed", 
        "check_run_url": "https://api.github.com/repos/CHChang810716/hunter/check-runs/1524527639", 
        "name": "Arkitekto sanitize-leak-cxx17 ubuntu-16.04", 
        "run_id": 410814899, 
        "url": "https://api.github.com/repos/CHChang810716/hunter/actions/jobs/1524527639", 
        "html_url": "https://github.com/CHChang810716/hunter/runs/1524527639", 
        "completed_at": "2020-12-09T14:34:14Z", 
        "run_url": "https://api.github.com/repos/CHChang810716/hunter/actions/runs/410814899", 
        "node_id": "MDg6Q2hlY2tSdW4xNTI0NTI3NjM5", 
        "steps": [
            {
                "status": "completed", 
                "name": "Set up job", 
                "number": 1, 
                "completed_at": "2020-12-09T14:33:59.000Z", 
                "started_at": "2020-12-09T14:33:55.000Z", 
                "conclusion": "success"
            }, 
            {
                "status": "completed", 
                "name": "Git checkout with submodules", 
                "number": 2, 
                "completed_at": "2020-12-09T14:34:03.000Z", 
                "started_at": "2020-12-09T14:33:59.000Z", 
                "conclusion": "success"
            }, 
            {
                "status": "completed", 
                "name": "Set up Python", 
                "number": 3, 
                "completed_at": "2020-12-09T14:34:03.000Z", 
                "started_at": "2020-12-09T14:34:03.000Z", 
                "conclusion": "success"
            }, 
            {
                "status": "completed", 
                "name": "Set up Python environment variable (Unix)", 
                "number": 4, 
                "completed_at": "2020-12-09T14:34:03.000Z", 
                "started_at": "2020-12-09T14:34:03.000Z", 
                "conclusion": "success"
            }, 
            {
                "status": "completed", 
                "name": "Set up Python environment variable (Windows)", 
                "number": 5, 
                "completed_at": "2020-12-09T14:34:03.000Z", 
                "started_at": "2020-12-09T14:34:03.000Z", 
                "conclusion": "skipped"
            }, 
            {
                "status": "completed", 
                "name": "Extract branch name", 
                "number": 6, 
                "completed_at": "2020-12-09T14:34:03.000Z", 
                "started_at": "2020-12-09T14:34:03.000Z", 
                "conclusion": "success"
            }, 
            {
                "status": "completed", 
                "name": "Upgrade pip", 
                "number": 7, 
                "completed_at": "2020-12-09T14:34:07.000Z", 
                "started_at": "2020-12-09T14:34:03.000Z", 
                "conclusion": "success"
            }, 
            {
                "status": "completed", 
                "name": "Build on Unix", 
                "number": 8, 
                "completed_at": "2020-12-09T14:34:14.000Z", 
                "started_at": "2020-12-09T14:34:07.000Z", 
                "conclusion": "failure"
            }, 
            {
                "status": "completed", 
                "name": "Build on Windows", 
                "number": 9, 
                "completed_at": "2020-12-09T14:34:14.000Z", 
                "started_at": "2020-12-09T14:34:14.000Z", 
                "conclusion": "skipped"
            }, 
            {
                "status": "completed", 
                "name": "Post Git checkout with submodules", 
                "number": 18, 
                "completed_at": "2020-12-09T14:34:14.000Z", 
                "started_at": "2020-12-09T14:34:14.000Z", 
                "conclusion": "success"
            }, 
            {
                "status": "completed", 
                "name": "Complete job", 
                "number": 19, 
                "completed_at": "2020-12-09T14:34:14.000Z", 
                "started_at": "2020-12-09T14:34:14.000Z", 
                "conclusion": "success"
            }
        ], 
        "head_sha": "950960e8f1d67f7bc64155417f4a8e8ccebbad64", 
        "started_at": "2020-12-09T14:33:55Z", 
        "id": 1524527639, 
        "conclusion": "failure"
    }, 
    {
        "status": "completed", 
        "check_run_url": "https://api.github.com/repos/CHChang810716/hunter/check-runs/1524527655", 
        "name": "Arkitekto sanitize-thread-cxx17 ubuntu-16.04", 
        "run_id": 410814899, 
        "url": "https://api.github.com/repos/CHChang810716/hunter/actions/jobs/1524527655", 
        "html_url": "https://github.com/CHChang810716/hunter/runs/1524527655", 
        "completed_at": "2020-12-09T14:34:30Z", 
        "run_url": "https://api.github.com/repos/CHChang810716/hunter/actions/runs/410814899", 
        "node_id": "MDg6Q2hlY2tSdW4xNTI0NTI3NjU1", 
        "steps": [
            {
                "status": "completed", 
                "name": "Set up job", 
                "number": 1, 
                "completed_at": "2020-12-09T14:34:17.000Z", 
                "started_at": "2020-12-09T14:34:14.000Z", 
                "conclusion": "success"
            }, 
            {
                "status": "completed", 
                "name": "Git checkout with submodules", 
                "number": 2, 
                "completed_at": "2020-12-09T14:34:21.000Z", 
                "started_at": "2020-12-09T14:34:17.000Z", 
                "conclusion": "success"
            }, 
            {
                "status": "completed", 
                "name": "Set up Python", 
                "number": 3, 
                "completed_at": "2020-12-09T14:34:21.000Z", 
                "started_at": "2020-12-09T14:34:21.000Z", 
                "conclusion": "success"
            }, 
            {
                "status": "completed", 
                "name": "Set up Python environment variable (Unix)", 
                "number": 4, 
                "completed_at": "2020-12-09T14:34:21.000Z", 
                "started_at": "2020-12-09T14:34:21.000Z", 
                "conclusion": "success"
            }, 
            {
                "status": "completed", 
                "name": "Set up Python environment variable (Windows)", 
                "number": 5, 
                "completed_at": "2020-12-09T14:34:21.000Z", 
                "started_at": "2020-12-09T14:34:21.000Z", 
                "conclusion": "skipped"
            }, 
            {
                "status": "completed", 
                "name": "Extract branch name", 
                "number": 6, 
                "completed_at": "2020-12-09T14:34:21.000Z", 
                "started_at": "2020-12-09T14:34:21.000Z", 
                "conclusion": "success"
            }, 
            {
                "status": "completed", 
                "name": "Upgrade pip", 
                "number": 7, 
                "completed_at": "2020-12-09T14:34:24.000Z", 
                "started_at": "2020-12-09T14:34:21.000Z", 
                "conclusion": "success"
            }, 
            {
                "status": "completed", 
                "name": "Build on Unix", 
                "number": 8, 
                "completed_at": "2020-12-09T14:34:29.000Z", 
                "started_at": "2020-12-09T14:34:24.000Z", 
                "conclusion": "failure"
            }, 
            {
                "status": "completed", 
                "name": "Build on Windows", 
                "number": 9, 
                "completed_at": "2020-12-09T14:34:29.000Z", 
                "started_at": "2020-12-09T14:34:29.000Z", 
                "conclusion": "skipped"
            }, 
            {
                "status": "completed", 
                "name": "Post Git checkout with submodules", 
                "number": 18, 
                "completed_at": "2020-12-09T14:34:30.000Z", 
                "started_at": "2020-12-09T14:34:29.000Z", 
                "conclusion": "success"
            }, 
            {
                "status": "completed", 
                "name": "Complete job", 
                "number": 19, 
                "completed_at": "2020-12-09T14:34:30.000Z", 
                "started_at": "2020-12-09T14:34:30.000Z", 
                "conclusion": "success"
            }
        ], 
        "head_sha": "950960e8f1d67f7bc64155417f4a8e8ccebbad64", 
        "started_at": "2020-12-09T14:34:14Z", 
        "id": 1524527655, 
        "conclusion": "failure"
    }, 
    {
        "status": "completed", 
        "check_run_url": "https://api.github.com/repos/CHChang810716/hunter/check-runs/1524527836", 
        "name": "Arkitekto vs-14-2015-sdk-8-1 windows-2016", 
        "run_id": 410814899, 
        "url": "https://api.github.com/repos/CHChang810716/hunter/actions/jobs/1524527836", 
        "html_url": "https://github.com/CHChang810716/hunter/runs/1524527836", 
        "completed_at": "2020-12-09T14:35:05Z", 
        "run_url": "https://api.github.com/repos/CHChang810716/hunter/actions/runs/410814899", 
        "node_id": "MDg6Q2hlY2tSdW4xNTI0NTI3ODM2", 
        "steps": [
            {
                "status": "completed", 
                "name": "Set up job", 
                "number": 1, 
                "completed_at": "2020-12-09T14:34:25.000Z", 
                "started_at": "2020-12-09T14:34:22.000Z", 
                "conclusion": "success"
            }, 
            {
                "status": "completed", 
                "name": "Git checkout with submodules", 
                "number": 2, 
                "completed_at": "2020-12-09T14:34:39.000Z", 
                "started_at": "2020-12-09T14:34:25.000Z", 
                "conclusion": "success"
            }, 
            {
                "status": "completed", 
                "name": "Set up Python", 
                "number": 3, 
                "completed_at": "2020-12-09T14:34:39.000Z", 
                "started_at": "2020-12-09T14:34:39.000Z", 
                "conclusion": "success"
            }, 
            {
                "status": "completed", 
                "name": "Set up Python environment variable (Unix)", 
                "number": 4, 
                "completed_at": "2020-12-09T14:34:39.000Z", 
                "started_at": "2020-12-09T14:34:39.000Z", 
                "conclusion": "skipped"
            }, 
            {
                "status": "completed", 
                "name": "Set up Python environment variable (Windows)", 
                "number": 5, 
                "completed_at": "2020-12-09T14:34:40.000Z", 
                "started_at": "2020-12-09T14:34:39.000Z", 
                "conclusion": "success"
            }, 
            {
                "status": "completed", 
                "name": "Extract branch name", 
                "number": 6, 
                "completed_at": "2020-12-09T14:34:40.000Z", 
                "started_at": "2020-12-09T14:34:40.000Z", 
                "conclusion": "success"
            }, 
            {
                "status": "completed", 
                "name": "Upgrade pip", 
                "number": 7, 
                "completed_at": "2020-12-09T14:34:47.000Z", 
                "started_at": "2020-12-09T14:34:40.000Z", 
                "conclusion": "success"
            }, 
            {
                "status": "completed", 
                "name": "Build on Unix", 
                "number": 8, 
                "completed_at": "2020-12-09T14:34:47.000Z", 
                "started_at": "2020-12-09T14:34:47.000Z", 
                "conclusion": "skipped"
            }, 
            {
                "status": "completed", 
                "name": "Build on Windows", 
                "number": 9, 
                "completed_at": "2020-12-09T14:35:02.000Z", 
                "started_at": "2020-12-09T14:34:47.000Z", 
                "conclusion": "failure"
            }, 
            {
                "status": "completed", 
                "name": "Post Git checkout with submodules", 
                "number": 18, 
                "completed_at": "2020-12-09T14:35:05.000Z", 
                "started_at": "2020-12-09T14:35:02.000Z", 
                "conclusion": "success"
            }, 
            {
                "status": "completed", 
                "name": "Complete job", 
                "number": 19, 
                "completed_at": "2020-12-09T14:35:05.000Z", 
                "started_at": "2020-12-09T14:35:05.000Z", 
                "conclusion": "success"
            }
        ], 
        "head_sha": "950960e8f1d67f7bc64155417f4a8e8ccebbad64", 
        "started_at": "2020-12-09T14:34:22Z", 
        "id": 1524527836, 
        "conclusion": "failure"
    }, 
    {
        "status": "completed", 
        "check_run_url": "https://api.github.com/repos/CHChang810716/hunter/check-runs/1524527822", 
        "name": "Arkitekto vs-15-2017-win64-cxx17 windows-2016", 
        "run_id": 410814899, 
        "url": "https://api.github.com/repos/CHChang810716/hunter/actions/jobs/1524527822", 
        "html_url": "https://github.com/CHChang810716/hunter/runs/1524527822", 
        "completed_at": "2020-12-09T14:35:09Z", 
        "run_url": "https://api.github.com/repos/CHChang810716/hunter/actions/runs/410814899", 
        "node_id": "MDg6Q2hlY2tSdW4xNTI0NTI3ODIy", 
        "steps": [
            {
                "status": "completed", 
                "name": "Set up job", 
                "number": 1, 
                "completed_at": "2020-12-09T14:34:29.000Z", 
                "started_at": "2020-12-09T14:34:26.000Z", 
                "conclusion": "success"
            }, 
            {
                "status": "completed", 
                "name": "Git checkout with submodules", 
                "number": 2, 
                "completed_at": "2020-12-09T14:34:42.000Z", 
                "started_at": "2020-12-09T14:34:29.000Z", 
                "conclusion": "success"
            }, 
            {
                "status": "completed", 
                "name": "Set up Python", 
                "number": 3, 
                "completed_at": "2020-12-09T14:34:42.000Z", 
                "started_at": "2020-12-09T14:34:42.000Z", 
                "conclusion": "success"
            }, 
            {
                "status": "completed", 
                "name": "Set up Python environment variable (Unix)", 
                "number": 4, 
                "completed_at": "2020-12-09T14:34:42.000Z", 
                "started_at": "2020-12-09T14:34:42.000Z", 
                "conclusion": "skipped"
            }, 
            {
                "status": "completed", 
                "name": "Set up Python environment variable (Windows)", 
                "number": 5, 
                "completed_at": "2020-12-09T14:34:43.000Z", 
                "started_at": "2020-12-09T14:34:42.000Z", 
                "conclusion": "success"
            }, 
            {
                "status": "completed", 
                "name": "Extract branch name", 
                "number": 6, 
                "completed_at": "2020-12-09T14:34:43.000Z", 
                "started_at": "2020-12-09T14:34:43.000Z", 
                "conclusion": "success"
            }, 
            {
                "status": "completed", 
                "name": "Upgrade pip", 
                "number": 7, 
                "completed_at": "2020-12-09T14:34:50.000Z", 
                "started_at": "2020-12-09T14:34:43.000Z", 
                "conclusion": "success"
            }, 
            {
                "status": "completed", 
                "name": "Build on Unix", 
                "number": 8, 
                "completed_at": "2020-12-09T14:34:50.000Z", 
                "started_at": "2020-12-09T14:34:50.000Z", 
                "conclusion": "skipped"
            }, 
            {
                "status": "completed", 
                "name": "Build on Windows", 
                "number": 9, 
                "completed_at": "2020-12-09T14:35:06.000Z", 
                "started_at": "2020-12-09T14:34:50.000Z", 
                "conclusion": "failure"
            }, 
            {
                "status": "completed", 
                "name": "Post Git checkout with submodules", 
                "number": 18, 
                "completed_at": "2020-12-09T14:35:09.000Z", 
                "started_at": "2020-12-09T14:35:06.000Z", 
                "conclusion": "success"
            }, 
            {
                "status": "completed", 
                "name": "Complete job", 
                "number": 19, 
                "completed_at": "2020-12-09T14:35:09.000Z", 
                "started_at": "2020-12-09T14:35:09.000Z", 
                "conclusion": "success"
            }
        ], 
        "head_sha": "950960e8f1d67f7bc64155417f4a8e8ccebbad64", 
        "started_at": "2020-12-09T14:34:26Z", 
        "id": 1524527822, 
        "conclusion": "failure"
    }, 
    {
        "status": "completed", 
        "check_run_url": "https://api.github.com/repos/CHChang810716/hunter/check-runs/1524527798", 
        "name": "Arkitekto vs-16-2019-win64-cxx17 windows-2019", 
        "run_id": 410814899, 
        "url": "https://api.github.com/repos/CHChang810716/hunter/actions/jobs/1524527798", 
        "html_url": "https://github.com/CHChang810716/hunter/runs/1524527798", 
        "completed_at": "2020-12-09T14:35:30Z", 
        "run_url": "https://api.github.com/repos/CHChang810716/hunter/actions/runs/410814899", 
        "node_id": "MDg6Q2hlY2tSdW4xNTI0NTI3Nzk4", 
        "steps": [
            {
                "status": "completed", 
                "name": "Set up job", 
                "number": 1, 
                "completed_at": "2020-12-09T14:34:31.000Z", 
                "started_at": "2020-12-09T14:34:27.000Z", 
                "conclusion": "success"
            }, 
            {
                "status": "completed", 
                "name": "Git checkout with submodules", 
                "number": 2, 
                "completed_at": "2020-12-09T14:34:51.000Z", 
                "started_at": "2020-12-09T14:34:31.000Z", 
                "conclusion": "success"
            }, 
            {
                "status": "completed", 
                "name": "Set up Python", 
                "number": 3, 
                "completed_at": "2020-12-09T14:34:51.000Z", 
                "started_at": "2020-12-09T14:34:51.000Z", 
                "conclusion": "success"
            }, 
            {
                "status": "completed", 
                "name": "Set up Python environment variable (Unix)", 
                "number": 4, 
                "completed_at": "2020-12-09T14:34:51.000Z", 
                "started_at": "2020-12-09T14:34:51.000Z", 
                "conclusion": "skipped"
            }, 
            {
                "status": "completed", 
                "name": "Set up Python environment variable (Windows)", 
                "number": 5, 
                "completed_at": "2020-12-09T14:34:53.000Z", 
                "started_at": "2020-12-09T14:34:51.000Z", 
                "conclusion": "success"
            }, 
            {
                "status": "completed", 
                "name": "Extract branch name", 
                "number": 6, 
                "completed_at": "2020-12-09T14:34:53.000Z", 
                "started_at": "2020-12-09T14:34:53.000Z", 
                "conclusion": "success"
            }, 
            {
                "status": "completed", 
                "name": "Upgrade pip", 
                "number": 7, 
                "completed_at": "2020-12-09T14:35:07.000Z", 
                "started_at": "2020-12-09T14:34:53.000Z", 
                "conclusion": "success"
            }, 
            {
                "status": "completed", 
                "name": "Build on Unix", 
                "number": 8, 
                "completed_at": "2020-12-09T14:35:07.000Z", 
                "started_at": "2020-12-09T14:35:07.000Z", 
                "conclusion": "skipped"
            }, 
            {
                "status": "completed", 
                "name": "Build on Windows", 
                "number": 9, 
                "completed_at": "2020-12-09T14:35:27.000Z", 
                "started_at": "2020-12-09T14:35:07.000Z", 
                "conclusion": "failure"
            }, 
            {
                "status": "completed", 
                "name": "Post Git checkout with submodules", 
                "number": 18, 
                "completed_at": "2020-12-09T14:35:30.000Z", 
                "started_at": "2020-12-09T14:35:27.000Z", 
                "conclusion": "success"
            }, 
            {
                "status": "completed", 
                "name": "Complete job", 
                "number": 19, 
                "completed_at": "2020-12-09T14:35:30.000Z", 
                "started_at": "2020-12-09T14:35:30.000Z", 
                "conclusion": "success"
            }
        ], 
        "head_sha": "950960e8f1d67f7bc64155417f4a8e8ccebbad64", 
        "started_at": "2020-12-09T14:34:27Z", 
        "id": 1524527798, 
        "conclusion": "failure"
    }
]